batman/__init__.py
batman/_custom_ld.cpython-311-x86_64-linux-gnu.so
batman/_eclipse.cpython-311-x86_64-linux-gnu.so
batman/_exponential_ld.cpython-311-x86_64-linux-gnu.so
batman/_logarithmic_ld.cpython-311-x86_64-linux-gnu.so
batman/_nonlinear_ld.cpython-311-x86_64-linux-gnu.so
batman/_power2_ld.cpython-311-x86_64-linux-gnu.so
batman/_quadratic_ld.cpython-311-x86_64-linux-gnu.so
batman/_rsky.cpython-311-x86_64-linux-gnu.so
batman/_uniform_ld.cpython-311-x86_64-linux-gnu.so
batman/openmp.py
batman/plots.py
batman/tests.py
batman/transitmodel.py
batman_package.libs/libgomp-a34b3233.so.1.0.0
batman_package-2.5.3.dist-info/METADATA
batman_package-2.5.3.dist-info/WHEEL
batman_package-2.5.3.dist-info/top_level.txt
batman_package-2.5.3.dist-info/RECORD
batman_package-2.5.3.dist-info/licenses/LICENSE.txt
