Metadata-Version: 2.4
Name: batman-package
Version: 2.5.3
Summary: Fast transit light curve modeling
Home-page: https://github.com/lkreidberg/batman
Author: Laura Kreidberg
Author-email: laura.kreidberg@gmail.com
License: GNU GPLv3
Classifier: Development Status :: 5 - Production/Stable
Classifier: Intended Audience :: Science/Research
Classifier: Topic :: Scientific/Engineering
Classifier: Programming Language :: Python
License-File: LICENSE.txt
Requires-Dist: numpy
Provides-Extra: matplotlib
Requires-Dist: matplotlib; extra == "matplotlib"
Dynamic: author
Dynamic: author-email
Dynamic: classifier
Dynamic: home-page
Dynamic: license
Dynamic: license-file
Dynamic: provides-extra
Dynamic: requires-dist
Dynamic: summary
